AreaNinja/__init__.py
AreaNinja/circle.py
AreaNinja/geometry.py
AreaNinja/rectangle.py
AreaNinja/triangle.py
areaninja-0.1.4.dist-info/METADATA
areaninja-0.1.4.dist-info/WHEEL
areaninja-0.1.4.dist-info/top_level.txt
areaninja-0.1.4.dist-info/RECORD
