Metadata-Version: 2.4
Name: AreaNinja
Version: 0.1.4
Summary: Library for calculating the area of geometric shapes
Author-email: Kirill Domitin <domitin@gmail.com>
Requires-Python: >=3.7
